__init__.py
taskllm/__init__.py
taskllm/ai.py
taskllm/instrument.py
taskllm/py.typed
taskllm/utils.py
taskllm/optimizer/__init__.py
taskllm/optimizer/data.py
taskllm/optimizer/methods/__init__.py
taskllm/optimizer/methods/bandit.py
taskllm/optimizer/methods/base.py
taskllm/optimizer/methods/bayesian.py
taskllm/optimizer/metrics/__init__.py
taskllm/optimizer/metrics/classification.py
taskllm/optimizer/prompt/ai.py
taskllm/optimizer/prompt/meta.py
taskllm-0.1.0.dist-info/METADATA
taskllm-0.1.0.dist-info/WHEEL
taskllm-0.1.0.dist-info/top_level.txt
taskllm-0.1.0.dist-info/RECORD
