Metadata-Version: 2.4
Name: taskllm
Version: 0.1.0
Summary: A library for optimizing LLM tasks, including prompt engineering and bandit-based training.
Requires-Python: >=3.11
Requires-Dist: aioconsole>=0.8.1
Requires-Dist: diskcache>=5.6.3
Requires-Dist: instructor>=1.0
Requires-Dist: jinja2>=3.1.6
Requires-Dist: litellm>=1.67.2
Requires-Dist: loguru>=0.7.3
Requires-Dist: pydantic>=2.11.3
Requires-Dist: pymc>=5.22.0
Requires-Dist: rich>=13.0
Requires-Dist: scikit-learn>=1.6.1
